{
  "heroes": {
    "WARRIOR": "male1.png",
    "KNIGHT": "male2.png", 
    "PALADIN": "male3.png",
    "MAGE": "male4.png",
    "WIZARD": "male5.png",
    "NECROMANCER": "male6.png",
    "ARCHER": "male7.png",
    "RANGER": "male8.png",
    "DRUID": "male9.png",
    "CLERIC": "male10.png",
    "ROGUE": "male11.png",
    "BARBARIAN": "male12.png",
    "WARRIOR_F": "female1.png",
    "MAGE_F": "female2.png",
    "ARCHER_F": "female3.png",
    "ROGUE_F": "female4.png",
    "PALADIN_F": "female5.png",
    "NECROMANCER_F": "female6.png"
  },
  "fallback": "male1.png",
  "style": "flare-semi-realistic",
  "format": "Various PNG sizes",
  "license": "CC-BY-SA 3.0"
}
